phonikud/__init__.py
phonikud/hebrew.py
phonikud/lexicon.py
phonikud/log.py
phonikud/phonemize.py
phonikud/syllables.py
phonikud/utils.py
phonikud/variants.py
phonikud/data/rashej_tevot.json
phonikud/data/special.json
phonikud/data/symbols.json
phonikud/expander/__init__.py
phonikud/expander/dates.py
phonikud/expander/dictionary.py
phonikud/expander/number_names.py
phonikud/expander/numbers.py
phonikud/expander/time_to_word.py
phonikud-0.4.1.dist-info/METADATA
phonikud-0.4.1.dist-info/WHEEL
phonikud-0.4.1.dist-info/licenses/LICENSE
phonikud-0.4.1.dist-info/RECORD
