Metadata-Version: 2.4
Name: phonikud
Version: 0.4.1
Summary: Convert Hebrew text into IPA for TTS systems and learning
Project-URL: Homepage, https://github.com/thewh1teagle/phonikud
Project-URL: Repository, https://github.com/thewh1teagle/phonikud
Project-URL: Issues, https://github.com/thewh1teagle/phonikud/issues
Author-email: thewh1teagle <61390950+thewh1teagle@users.noreply.github.com>
License-File: LICENSE
Requires-Python: <3.13,>=3.8
Requires-Dist: colorlog>=6.9.0
Requires-Dist: num2words>=0.5.14
Requires-Dist: regex>=2024.11.6
